jupytercad_mcp/__init__.py
jupytercad_mcp/server.py
jupytercad_mcp-0.1.1.dist-info/WHEEL
jupytercad_mcp-0.1.1.dist-info/entry_points.txt
jupytercad_mcp-0.1.1.dist-info/METADATA
jupytercad_mcp-0.1.1.dist-info/RECORD
