Metadata-Version: 2.4
Name: jupytercad-mcp
Version: 0.1.1
Summary: An MCP server for JupyterCAD that allows you to control it using natural language.
Keywords: jupytercad,jupyterlab,mcp,computer-aided design,cad
Author: asmith26
License-Expression: Apache-2.0
Classifier: Programming Language :: Python :: 3
Classifier: Programming Language :: Python :: 3.10
Classifier: Programming Language :: Python :: 3.11
Classifier: Programming Language :: Python :: 3.12
Classifier: Programming Language :: Python :: 3.13
Requires-Dist: jupytercad>=3.1.6
Requires-Dist: mcp>=1.16.0
Requires-Dist: mlflow>=3.2.0 ; extra == 'examples'
Requires-Dist: openai-agents[litellm]>=0.2.11 ; extra == 'examples'
Requires-Python: >=3.10
Project-URL: Homepage, https://github.com/asmith26/jupytercad-mcp
Provides-Extra: examples
